PySDDP/Pde.py
PySDDP/Pen.py
PySDDP/Pmo.py
PySDDP/PowerSystem.py
PySDDP/__init__.py
PySDDP/dadosgerais.py
PySDDP/fcf.py
PySDDP/hidr.py
PySDDP/interc.py
PySDDP/mixins.py
PySDDP/planerg.py
PySDDP/pmo_old.py
PySDDP/resequiv.py
PySDDP/submercado.py
PySDDP/term.py
PySDDP/decomp/__init__.py
PySDDP/decomp/script/__init__.py
PySDDP/decomp/script/caso.py
PySDDP/decomp/script/dadgnl.py
PySDDP/decomp/script/hidr.py
PySDDP/decomp/script/indice.py
PySDDP/decomp/script/perdas.py
PySDDP/decomp/script/polinjus.py
PySDDP/decomp/script/vazoes.py
PySDDP/decomp/script/templates/__init__.py
PySDDP/decomp/script/templates/arquivo_entrada.py
PySDDP/decomp/script/templates/caso.py
PySDDP/decomp/script/templates/dadgnl.py
PySDDP/decomp/script/templates/hidr.py
PySDDP/decomp/script/templates/indice.py
PySDDP/decomp/script/templates/perdas.py
PySDDP/decomp/script/templates/polinjus.py
PySDDP/decomp/script/templates/vazoes.py
PySDDP/dessem/__init__.py
PySDDP/dessem/script/__init__.py
PySDDP/dessem/script/areacont.py
PySDDP/dessem/script/arquivos.py
PySDDP/dessem/script/bateria.py
PySDDP/dessem/script/cadterm.py
PySDDP/dessem/script/cotasr11.py
PySDDP/dessem/script/curvtviag.py
PySDDP/dessem/script/dadger.py
PySDDP/dessem/script/dados_eletricos.py
PySDDP/dessem/script/dadvaz.py
PySDDP/dessem/script/deflant.py
PySDDP/dessem/script/dessopc.py
PySDDP/dessem/script/eolica.py
PySDDP/dessem/script/hidr.py
PySDDP/dessem/script/ilibs.py
PySDDP/dessem/script/ilstri.py
PySDDP/dessem/script/indelet.py
PySDDP/dessem/script/infofcf.py
PySDDP/dessem/script/operuh.py
PySDDP/dessem/script/operut.py
PySDDP/dessem/script/polinjus.py
PySDDP/dessem/script/ptoper.py
PySDDP/dessem/script/rampas.py
PySDDP/dessem/script/respot.py
PySDDP/dessem/script/respotele.py
PySDDP/dessem/script/restseg.py
PySDDP/dessem/script/rmpflx.py
PySDDP/dessem/script/rstlpp.py
PySDDP/dessem/script/simul.py
PySDDP/dessem/script/solar.py
PySDDP/dessem/script/tolperd.py
PySDDP/dessem/script/vazao_lateral.py
PySDDP-0.0.65.dist-info/LICENSE.txt
PySDDP-0.0.65.dist-info/METADATA
PySDDP-0.0.65.dist-info/WHEEL
PySDDP-0.0.65.dist-info/top_level.txt
PySDDP-0.0.65.dist-info/RECORD
