Metadata-Version: 2.1
Name: PySDDP
Version: 0.0.65
Summary: PySDDP package
Home-page: https://github.com/AndreMarcato/PySDDP
Author: Andre Marcato
Author-email: andre.marcato@ufjf.edu.br
License: MIT
Keywords: pysddp
Platform: UNKNOWN
Classifier: Development Status :: 5 - Production/Stable
Classifier: Intended Audience :: Developers
Classifier: Intended Audience :: Education
Classifier: License :: OSI Approved :: MIT License
Classifier: Operating System :: OS Independent
Classifier: Topic :: Scientific/Engineering :: Information Analysis
Classifier: Programming Language :: Python :: 3
Classifier: Programming Language :: Python :: 3.9
Classifier: Programming Language :: Python :: 3 :: Only
Requires-Python: >=3
License-File: LICENSE.txt
Requires-Dist: numpy
Requires-Dist: matplotlib
Requires-Dist: cvxopt
Requires-Dist: pyswarm
Requires-Dist: scipy
Requires-Dist: typing
Requires-Dist: pandas
